setup.py
ec2util/__init__.py
ec2util/aws.py
ec2util/ec2util.py
ec2util.egg-info/PKG-INFO
ec2util.egg-info/SOURCES.txt
ec2util.egg-info/dependency_links.txt
ec2util.egg-info/entry_points.txt
ec2util.egg-info/requires.txt
ec2util.egg-info/top_level.txt