Metadata-Version: 1.0
Name: ec2util
Version: 0.1.5
Summary: Performs common ec2 tasks on the command line. Written in Python, based on boto.
Home-page: https://github.com/laszlocph/ec2util.git
Author: laszlocph
Author-email: laszlo@falconsocial.com
License: UNKNOWN
Platform: UNKNOWN
